diagrams_net_automation/__init__.py
diagrams_net_automation/converter.py
diagrams_net_automation/main.py
diagrams_net_automation/utils.py
diagrams_net_automation-0.1.8.dist-info/entry_points.txt
diagrams_net_automation-0.1.8.dist-info/LICENSE
diagrams_net_automation-0.1.8.dist-info/WHEEL
diagrams_net_automation-0.1.8.dist-info/METADATA
diagrams_net_automation-0.1.8.dist-info/RECORD
