Metadata-Version: 2.1
Name: diagrams-net-automation
Version: 0.1.8
Summary: Scripts to automatically covert diagrams.net files, e.g., to PDF.
Home-page: https://github.com/pstoeckle/Diagrams.net-Automation.get
License: Apache-2.0
Author: Patrick Stöckle
Author-email: patrick.stoeckle@posteo.de
Maintainer: Patrick Stöckle
Maintainer-email: patrick.stoeckle@posteo.de
Requires-Python: >=3.7,<4.0
Classifier: License :: OSI Approved :: Apache Software License
Classifier: Programming Language :: Python :: 3
Classifier: Programming Language :: Python :: 3.7
Classifier: Programming Language :: Python :: 3.8
Classifier: Programming Language :: Python :: 3.9
Classifier: Programming Language :: Python :: 3.10
Classifier: Programming Language :: Python :: 3.11
Requires-Dist: lxml (>=4.9.1,<5.0.0)
Requires-Dist: tqdm (>=4.64.1,<5.0.0)
Requires-Dist: typer (>=0.7.0,<0.8.0)
Project-URL: Repository, https://github.com/pstoeckle/Diagrams.net-Automation.get
